world_class/__init__.py
world_class-0.1.3.dist-info/LICENSE
world_class-0.1.3.dist-info/METADATA
world_class-0.1.3.dist-info/WHEEL
world_class-0.1.3.dist-info/top_level.txt
world_class-0.1.3.dist-info/RECORD
