Metadata-Version: 2.1
Name: world-class
Version: 0.1.3
Summary: A mixture of ISO 3166-1 Alpha-2 Country codes, ISO 639-1 Language codes and ISO-4217 Currency codes.
Home-page: https://github.com/lvm/world-class
Author: Mauro Lizaur
Author-email: mauro@sdf.org
License: BSD 3-Clause License
Platform: UNKNOWN
Classifier: License :: OSI Approved :: BSD License
Classifier: Programming Language :: Python :: 3
Classifier: Programming Language :: Python :: 3.8
